LICENSE
README.md
setup.cfg
setup.py
trademaster411/__init__.py
trademaster411.egg-info/PKG-INFO
trademaster411.egg-info/SOURCES.txt
trademaster411.egg-info/dependency_links.txt
trademaster411.egg-info/requires.txt
trademaster411.egg-info/top_level.txt
trademaster411/agents/__init__.py
trademaster411/agents/builder.py
trademaster411/agents/custom.py
trademaster411/agents/algorithmic_trading/__init__.py
trademaster411/agents/algorithmic_trading/dqn.py
trademaster411/agents/high_frequency_trading/__init__.py
trademaster411/agents/high_frequency_trading/ddqn.py
trademaster411/agents/order_execution/__init__.py
trademaster411/agents/order_execution/eteo.py
trademaster411/agents/order_execution/pd.py
trademaster411/agents/portfolio_management/__init__.py
trademaster411/agents/portfolio_management/deeptrader.py
trademaster411/agents/portfolio_management/eiie.py
trademaster411/agents/portfolio_management/investor_imitator.py
trademaster411/collector/__init__.py
trademaster411/collector/binance.py
trademaster411/collector/builder.py
trademaster411/collector/custom.py
trademaster411/collector/helper/__init__.py
trademaster411/collector/helper/celery_app.py
trademaster411/collector/helper/celery_config.py
trademaster411/collector/helper/pika_connection.py
trademaster411/collector/helper/run_celery.py
trademaster411/collector/helper/websocket_consumer.py
trademaster411/collector/helper/websocket_producer.py
trademaster411/datasets/__init__.py
trademaster411/datasets/builder.py
trademaster411/datasets/custom.py
trademaster411/datasets/algorithmic_trading/__init__.py
trademaster411/datasets/algorithmic_trading/dataset.py
trademaster411/datasets/high_frequency_trading/__init__.py
trademaster411/datasets/high_frequency_trading/dataset.py
trademaster411/datasets/order_execution/__init__.py
trademaster411/datasets/order_execution/dataset.py
trademaster411/datasets/portfolio_management/__init__.py
trademaster411/datasets/portfolio_management/dataset.py
trademaster411/environments/__init__.py
trademaster411/environments/builder.py
trademaster411/environments/custom.py
trademaster411/environments/algorithmic_trading/__init__.py
